[
  {
    "id": 1,
    "section": "A",
    "theme": "Daily activities",
    "question": "Quelle image correspond le mieux à l'enregistrement ?",
    "options": [
      { "id": "A", "text": "Une personne boit un café", "image_prompt": "A person sitting at a café terrace drinking coffee, morning light" },
      { "id": "B", "text": "Une personne fait ses courses", "image_prompt": "A person pushing a shopping cart in a grocery store aisle" },
      { "id": "C", "text": "Une personne lit un journal", "image_prompt": "A person reading a newspaper on a park bench" },
      { "id": "D", "text": "Une personne conduit une voiture", "image_prompt": "A person driving a car in urban traffic" }
    ],
    "correct": 0,
    "transcript_fr": "Chaque matin, avant d'aller au travail, j'arrête toujours au café du coin pour prendre un bon espresso bien fort.",
    "transcript_en": "Every morning, before going to work, I always stop at the corner café to have a good strong espresso.",
    "points": [
      {
        "point": 1,
        "male_lines": ["Chaque matin, avant d'aller au travail, j'arrête toujours au café du coin pour prendre un bon espresso bien fort."],
        "female_lines": []
      }
    ]
  },
  {
    "id": 2,
    "section": "A",
    "theme": "Transportation",
    "question": "Quelle image correspond le mieux à l'enregistrement ?",
    "options": [
      { "id": "A", "text": "Un autobus scolaire", "image_prompt": "A yellow school bus stopped at a crosswalk" },
      { "id": "B", "text": "Un métro bondé", "image_prompt": "A crowded subway train with passengers standing" },
      { "id": "C", "text": "Un taxi en attente", "image_prompt": "A taxi waiting at a stand in front of a hotel" },
      { "id": "D", "text": "Un train à grande vitesse", "image_prompt": "A high-speed train arriving at a modern station" }
    ],
    "correct": 1,
    "transcript_fr": "L'heure de pointe dans le métro de Montréal est vraiment intense, on est serrés comme des sardines dans les wagons.",
    "transcript_en": "Rush hour in the Montreal metro is really intense, we're packed like sardines in the train cars.",
    "points": [
      {
        "point": 1,
        "male_lines": ["L'heure de pointe dans le métro de Montréal est vraiment intense, on est serrés comme des sardines dans les wagons."],
        "female_lines": []
      }
    ]
  },
  {
    "id": 3,
    "section": "A",
    "theme": "Weather",
    "question": "Quelle image correspond le mieux à l'enregistrement ?",
    "options": [
      { "id": "A", "text": "Une tempête de neige", "image_prompt": "A heavy snowstorm with low visibility in a city street" },
      { "id": "B", "text": "Une journée ensoleillée", "image_prompt": "A bright sunny day with clear blue sky" },
      { "id": "C", "text": "De la pluie torrentielle", "image_prompt": "Heavy rainfall with people holding umbrellas" },
      { "id": "D", "text": "Un ciel nuageux", "image_prompt": "An overcast cloudy sky with gray clouds" }
    ],
    "correct": 2,
    "transcript_fr": "Il pleut tellement fort dehors que je suis complètement trempé, même avec mon parapluie ça ne sert à rien!",
    "transcript_en": "It's raining so hard outside that I'm completely soaked, even with my umbrella it's useless!",
    "points": [
      {
        "point": 1,
        "male_lines": ["Il pleut tellement fort dehors que je suis complètement trempé, même avec mon parapluie ça ne sert à rien!"],
        "female_lines": []
      }
    ]
  },
  {
    "id": 4,
    "section": "A",
    "theme": "Food",
    "question": "Quelle image correspond le mieux à l'enregistrement ?",
    "options": [
      { "id": "A", "text": "Un restaurant fast-food", "image_prompt": "A fast-food restaurant with bright colors and counter service" },
      { "id": "B", "text": "Une pâtisserie française", "image_prompt": "A French pastry shop with croissants and cakes in the window" },
      { "id": "C", "text": "Un marché fermier", "image_prompt": "A farmers market with fresh vegetables and local products" },
      { "id": "D", "text": "Une cuisine à domicile", "image_prompt": "A home kitchen with someone cooking a meal" }
    ],
    "correct": 1,
    "transcript_fr": "La boulangerie sur la rue Saint-Denis fait les meilleurs croissants au beurre de toute la ville, c'est divin!",
    "transcript_en": "The bakery on Saint-Denis Street makes the best butter croissants in the whole city, it's divine!",
    "points": [
      {
        "point": 1,
        "male_lines": ["La boulangerie sur la rue Saint-Denis fait les meilleurs croissants au beurre de toute la ville, c'est divin!"],
        "female_lines": []
      }
    ]
  },
  {
    "id": 5,
    "section": "A",
    "theme": "Work",
    "question": "Quelle image correspond le mieux à l'enregistrement ?",
    "options": [
      { "id": "A", "text": "Un bureau moderne", "image_prompt": "A modern open-plan office with computers and glass walls" },
      { "id": "B", "text": "Un chantier de construction", "image_prompt": "A construction site with workers and heavy machinery" },
      { "id": "C", "text": "Une salle de réunion", "image_prompt": "A meeting room with people sitting around a conference table" },
      { "id": "D", "text": "Un espace de coworking", "image_prompt": "A coworking space with freelancers on laptops" }
    ],
    "correct": 0,
    "transcript_fr": "Notre nouveau bureau au centre-ville est super lumineux avec des fenêtres du plancher au plafond, c'est vraiment agréable.",
    "transcript_en": "Our new downtown office is super bright with floor-to-ceiling windows, it's really pleasant.",
    "points": [
      {
        "point": 1,
        "male_lines": ["Notre nouveau bureau au centre-ville est super lumineux avec des fenêtres du plancher au plafond, c'est vraiment agréable."],
        "female_lines": []
      }
    ]
  },
  {
    "id": 6,
    "section": "A",
    "theme": "Leisure",
    "question": "Quelle image correspond le mieux à l'enregistrement ?",
    "options": [
      { "id": "A", "text": "Un cinéma", "image_prompt": "A movie theater with red seats and a large screen" },
      { "id": "B", "text": "Un parc d'attractions", "image_prompt": "An amusement park with roller coasters and colorful rides" },
      { "id": "C", "text": "Une bibliothèque", "image_prompt": "A quiet library with bookshelves and people reading" },
      { "id": "D", "text": "Un centre sportif", "image_prompt": "A sports center with gym equipment and basketball courts" }
    ],
    "correct": 3,
    "transcript_fr": "Je vais au gym trois fois par semaine pour faire de la musculation et un peu de cardio, ça me fait du bien.",
    "transcript_en": "I go to the gym three times a week to do weight training and some cardio, it does me good.",
    "points": [
      {
        "point": 1,
        "male_lines": ["Je vais au gym trois fois par semaine pour faire de la musculation et un peu de cardio, ça me fait du bien."],
        "female_lines": []
      }
    ]
  },
  {
    "id": 7,
    "section": "B",
    "theme": "Shopping",
    "question": "Où se déroule cette conversation ?",
    "options": [
      { "id": "A", "text": "Dans une librairie", "image_prompt": "" },
      { "id": "B", "text": "Dans un magasin de vêtements", "image_prompt": "" },
      { "id": "C", "text": "Dans une pharmacie", "image_prompt": "" },
      { "id": "D", "text": "Dans un supermarché", "image_prompt": "" }
    ],
    "correct": 1,
    "transcript_fr": "Homme: Bonjour madame, je cherche un manteau d'hiver en taille moyenne. Femme: Oui, nous avons cette section ici à gauche. Les manteaux sont rangés par taille. Homme: Parfait, puis-je essayer celui-ci en bleu marine ? Femme: Bien sûr, les cabines d'essayage sont au fond du magasin à droite.",
    "transcript_en": "Man: Hello madam, I'm looking for a winter coat in medium size. Woman: Yes, we have this section here on the left. The coats are arranged by size. Man: Perfect, may I try this one in navy blue? Woman: Of course, the fitting rooms are at the back of the store on the right.",
    "points": [
      {
        "point": 1,
        "male_lines": ["Bonjour madame, je cherche un manteau d'hiver en taille moyenne."],
        "female_lines": ["Oui, nous avons cette section ici à gauche. Les manteaux sont rangés par taille."]
      },
      {
        "point": 2,
        "male_lines": ["Parfait, puis-je essayer celui-ci en bleu marine ?"],
        "female_lines": ["Bien sûr, les cabines d'essayage sont au fond du magasin à droite."]
      },
      {
        "point": 3,
        "male_lines": [],
        "female_lines": []
      },
      {
        "point": 4,
        "male_lines": [],
        "female_lines": []
      }
    ]
  },
  {
    "id": 8,
    "section": "B",
    "theme": "Restaurant",
    "question": "Quelle boisson le client commande-t-il ?",
    "options": [
      { "id": "A", "text": "Un café", "image_prompt": "" },
      { "id": "B", "text": "Un thé glacé", "image_prompt": "" },
      { "id": "C", "text": "Une bière locale", "image_prompt": "" },
      { "id": "D", "text": "Un verre de vin rouge", "image_prompt": "" }
    ],
    "correct": 2,
    "transcript_fr": "Serveuse: Bonsoir, avez-vous fait votre choix pour la boisson ? Client: Oui, je voudrais essayer votre bière locale brassée ici même. Serveuse: Excellente choix! La blonde ou la rousse ? Client: La blonde, s'il vous plaît. Serveuse: Très bien, je vous apporte ça tout de suite avec le menu.",
    "transcript_en": "Waitress: Good evening, have you made your choice for the drink? Customer: Yes, I would like to try your local beer brewed right here. Waitress: Excellent choice! The blonde or the red ale? Customer: The blonde, please. Waitress: Very well, I'll bring that right away with the menu.",
    "points": [
      {
        "point": 1,
        "male_lines": ["Bonsoir, avez-vous fait votre choix pour la boisson ?"],
        "female_lines": ["Oui, je voudrais essayer votre bière locale brassée ici même."]
      },
      {
        "point": 2,
        "male_lines": ["Excellente choix! La blonde ou la rousse ?"],
        "female_lines": ["La blonde, s'il vous plaît."]
      },
      {
        "point": 3,
        "male_lines": ["Très bien, je vous apporte ça tout de suite avec le menu."],
        "female_lines": []
      },
      {
        "point": 4,
        "male_lines": [],
        "female_lines": []
      }
    ]
  },
  {
    "id": 9,
    "section": "B",
    "theme": "Doctor",
    "question": "Quel est le problème du patient ?",
    "options": [
      { "id": "A", "text": "Il a mal à la tête", "image_prompt": "" },
      { "id": "B", "text": "Il s'est foulé la cheville", "image_prompt": "" },
      { "id": "C", "text": "Il a de la fièvre", "image_prompt": "" },
      { "id": "D", "text": "Il a mal au dos", "image_prompt": "" }
    ],
    "correct": 1,
    "transcript_fr": "Docteur: Alors, que se passe-t-il aujourd'hui ? Patient: Docteur, je me suis tordu la cheville en jouant au hockey hier soir. Docteur: Je vois, pouvez-vous marcher ? Patient: Oui mais avec beaucoup de difficulté, c'est très gonflé. Docteur: Nous allons faire une radiographie pour vérifier que ce n'est pas cassé.",
    "transcript_en": "Doctor: So, what's happening today? Patient: Doctor, I twisted my ankle playing hockey last night. Doctor: I see, can you walk? Patient: Yes but with great difficulty, it's very swollen. Doctor: We'll do an X-ray to check that it's not broken.",
    "points": [
      {
        "point": 1,
        "male_lines": ["Alors, que se passe-t-il aujourd'hui ?"],
        "female_lines": ["Docteur, je me suis tordu la cheville en jouant au hockey hier soir."]
      },
      {
        "point": 2,
        "male_lines": ["Je vois, pouvez-vous marcher ?"],
        "female_lines": ["Oui mais avec beaucoup de difficulté, c'est très gonflé."]
      },
      {
        "point": 3,
        "male_lines": ["Nous allons faire une radiographie pour vérifier que ce n'est pas cassé."],
        "female_lines": []
      },
      {
        "point": 4,
        "male_lines": [],
        "female_lines": []
      }
    ]
  },
  {
    "id": 10,
    "section": "B",
    "theme": "Bank",
    "question": "Pourquoi la cliente est-elle à la banque ?",
    "options": [
      { "id": "A", "text": "Pour ouvrir un compte", "image_prompt": "" },
      { "id": "B", "text": "Pour demander un prêt", "image_prompt": "" },
      { "id": "C", "text": "Pour déposer un chèque", "image_prompt": "" },
      { "id": "D", "text": "Pour changer son code PIN", "image_prompt": "" }
    ],
    "correct": 0,
    "transcript_fr": "Conseiller: Bonjour, bienvenue à la Banque Nationale. Comment puis-je vous aider ? Cliente: Bonjour, je viens d'emménager à Montréal et j'aimerais ouvrir un compte courant. Conseiller: Avec plaisir. Avez-vous vos pièces d'identité avec vous ? Cliente: Oui, voici mon passeport et mon permis de conduire. Conseiller: Parfait, remplissons les documents ensemble.",
    "transcript_en": "Advisor: Hello, welcome to National Bank. How can I help you? Client: Hello, I just moved to Montreal and I would like to open a checking account. Advisor: With pleasure. Do you have your identification documents with you? Client: Yes, here is my passport and driver's license. Advisor: Perfect, let's fill out the documents together.",
    "points": [
      {
        "point": 1,
        "male_lines": ["Bonjour, bienvenue à la Banque Nationale. Comment puis-je vous aider ?"],
        "female_lines": ["Bonjour, je viens d'emménager à Montréal et j'aimerais ouvrir un compte courant."]
      },
      {
        "point": 2,
        "male_lines": ["Avec plaisir. Avez-vous vos pièces d'identité avec vous ?"],
        "female_lines": ["Oui, voici mon passeport et mon permis de conduire."]
      },
      {
        "point": 3,
        "male_lines": ["Parfait, remplissons les documents ensemble."],
        "female_lines": []
      },
      {
        "point": 4,
        "male_lines": [],
        "female_lines": []
      }
    ]
  },
  {
    "id": 11,
    "section": "C",
    "theme": "Airport announcement",
    "question": "Quelle information est donnée dans cette annonce ?",
    "options": [
      { "id": "A", "text": "Un vol est retardé", "image_prompt": "" },
      { "id": "B", "text": "Un vol est annulé", "image_prompt": "" },
      { "id": "C", "text": "L'embarquement commence", "image_prompt": "" },
      { "id": "D", "text": "La récupération des bagages change", "image_prompt": "" }
    ],
    "correct": 0,
    "transcript_fr": "Mesdames et messieurs, nous avons le regret de vous informer que le vol AC457 à destination de Toronto est retardé d'une heure en raison des conditions météorologiques défavorables. L'embarquement débutera à 14h30 au lieu de 13h30. Nous vous prions de bien vouloir rester dans la zone d'embarquement et surveiller les écrans d'affichage. Nous vous offrons des bons de rafraîchissement au comptoir d'information. Nous vous remercions de votre compréhension et vous présentons nos excuses pour ce contretemps. L'équipe d'Air Canada.",
    "transcript_en": "Ladies and gentlemen, we regret to inform you that flight AC457 to Toronto is delayed by one hour due to unfavorable weather conditions. Boarding will begin at 2:30 PM instead of 1:30 PM. Please remain in the boarding area and monitor the display screens. We are offering refreshment vouchers at the information counter. We thank you for your understanding and apologize for this inconvenience. The Air Canada team.",
    "points": [
      {
        "point": 1,
        "male_lines": ["Mesdames et messieurs, nous avons le regret de vous informer que le vol AC457 à destination de Toronto est retardé d'une heure en raison des conditions météorologiques défavorables."],
        "female_lines": []
      },
      {
        "point": 2,
        "male_lines": ["L'embarquement débutera à 14h30 au lieu de 13h30."],
        "female_lines": []
      },
      {
        "point": 3,
        "male_lines": ["Nous vous prions de bien vouloir rester dans la zone d'embarquement et surveiller les écrans d'affichage."],
        "female_lines": []
      },
      {
        "point": 4,
        "male_lines": ["Nous vous offrons des bons de rafraîchissement au comptoir d'information."],
        "female_lines": []
      },
      {
        "point": 5,
        "male_lines": ["Nous vous remercions de votre compréhension et vous présentons nos excuses pour ce contretemps."],
        "female_lines": []
      },
      {
        "point": 6,
        "male_lines": ["L'équipe d'Air Canada."],
        "female_lines": []
      },
      {
        "point": 7,
        "male_lines": [],
        "female_lines": []
      },
      {
        "point": 8,
        "male_lines": [],
        "female_lines": []
      },
      {
        "point": 9,
        "male_lines": [],
        "female_lines": []
      },
      {
        "point": 10,
        "male_lines": [],
        "female_lines": []
      }
    ]
  },
  {
    "id": 12,
    "section": "C",
    "theme": "Supermarket announcement",
    "question": "Quelle promotion est annoncée ?",
    "options": [
      { "id": "A", "text": "50% sur les fruits", "image_prompt": "" },
      { "id": "B", "text": "Deux pour le prix d'un sur le fromage", "image_prompt": "" },
      { "id": "C", "text": "Rabais sur la viande fraîche", "imageprompt": "" },
      { "id": "D", "text": "Offre spéciale sur le pain", "image_prompt": "" }
    ],
    "correct": 2,
    "transcript_fr": "Chers clients, profitez de notre offre exceptionnelle aujourd'hui seulement sur tous les produits de boucherie frais. Le boeuf haché maigre est à 6,99$ la livre au lieu de 9,99$. Les côtelettes de porc sont en spécial à 4,50$ la livre. Cette promotion est valable jusqu'à la fermeture du magasin ce soir à 21 heures. Quantités limitées. Rendez-vous rapidement au rayon boucherie situé au fond du magasin à gauche. Merci de votre fidélité et bonne journée!",
    "transcript_en": "Dear customers, take advantage of our exceptional offer today only on all fresh butcher products. Lean ground beef is $6.99 per pound instead of $9.99. Pork chops are on special at $4.50 per pound. This promotion is valid until the store closes tonight at 9 PM. Limited quantities. Hurry to the butcher section located at the back of the store on the left. Thank you for your loyalty and have a good day!",
    "points": [
      {
        "point": 1,
        "male_lines": ["Chers clients, profitez de notre offre exceptionnelle aujourd'hui seulement sur tous les produits de boucherie frais."],
        "female_lines": []
      },
      {
        "point": 2,
        "male_lines": ["Le boeuf haché maigre est à 6,99$ la livre au lieu de 9,99$."],
        "female_lines": []
      },
      {
        "point": 3,
        "male_lines": ["Les côtelettes de porc sont en spécial à 4,50$ la livre."],
        "female_lines": []
      },
      {
        "point": 4,
        "male_lines": ["Cette promotion est valable jusqu'à la fermeture du magasin ce soir à 21 heures."],
        "female_lines": []
      },
      {
        "point": 5,
        "male_lines": ["Quantités limitées."],
        "female_lines": []
      },
      {
        "point": 6,
        "male_lines": ["Rendez-vous rapidement au rayon boucherie situé au fond du magasin à gauche."],
        "female_lines": []
      },
      {
        "point": 7,
        "male_lines": ["Merci de votre fidélité et bonne journée!"],
        "female_lines": []
      },
      {
        "point": 8,
        "male_lines": [],
        "female_lines": []
      },
      {
        "point": 9,
        "male_lines": [],
        "female_lines": []
      },
      {
        "point": 10,
        "male_lines": [],
        "female_lines": []
      }
    ]
  },
  {
    "id": 13,
    "section": "C",
    "theme": "University announcement",
    "question": "Quel changement est annoncé ?",
    "options": [
      { "id": "A", "text": "Les examens sont reportés", "image_prompt": "" },
      { "id": "B", "text": "Une bibliothèque ferme temporairement", "image_prompt": "" },
      { "id": "C", "text": "Les cours en ligne sont annulés", "image_prompt": "" },
      { "id": "D", "text": "Un professeur est remplacé", "image_prompt": "" }
    ],
    "correct": 1,
    "transcript_fr": "Attention étudiants, la bibliothèque principale du campus sera fermée pour rénovations du 15 au 30 mars prochain. Pendant cette période, les services de prêt seront transférés à la bibliothèque des sciences située dans le pavillon Marie-Victorin. Les heures d'ouverture restent les mêmes, de 8h à 22h du lundi au vendredi. Les ordinateurs et les salles d'étude groupe sont également disponibles sur réservation. Pour toute question, contactez le service aux étudiants au 514-343-6111. Merci de votre compréhension.",
    "transcript_en": "Attention students, the main campus library will be closed for renovations from March 15 to 30. During this period, loan services will be transferred to the science library located in the Marie-Victorin pavilion. Opening hours remain the same, from 8 AM to 10 PM Monday through Friday. Computers and group study rooms are also available by reservation. For any questions, contact student services at 514-343-6111. Thank you for your understanding.",
    "points": [
      {
        "point": 1,
        "male_lines": ["Attention étudiants, la bibliothèque principale du campus sera fermée pour rénovations du 15 au 30 mars prochain."],
        "female_lines": []
      },
      {
        "point": 2,
        "male_lines": ["Pendant cette période, les services de prêt seront transférés à la bibliothèque des sciences située dans le pavillon Marie-Victorin."],
        "female_lines": []
      },
      {
        "point": 3,
        "male_lines": ["Les heures d'ouverture restent les mêmes, de 8h à 22h du lundi au vendredi."],
        "female_lines": []
      },
      {
        "point": 4,
        "male_lines": ["Les ordinateurs et les salles d'étude groupe sont également disponibles sur réservation."],
        "female_lines": []
      },
      {
        "point": 5,
        "male_lines": ["Pour toute question, contactez le service aux étudiants au 514-343-6111."],
        "female_lines": []
      },
      {
        "point": 6,
        "male_lines": ["Merci de votre compréhension."],
        "female_lines": []
      },
      {
        "point": 7,
        "male_lines": [],
        "female_lines": []
      },
      {
        "point": 8,
        "male_lines": [],
        "female_lines": []
      },
      {
        "point": 9,
        "male_lines": [],
        "female_lines": []
      },
      {
        "point": 10,
        "male_lines": [],
        "female_lines": []
      }
    ]
  },
  {
    "id": 14,
    "section": "C",
    "theme": "Museum announcement",
    "question": "Quelle exposition est mentionnée ?",
    "options": [
      { "id": "A", "text": "Art moderne québécois", "image_prompt": "" },
      { "id": "B", "text": "Photographie contemporaine", "image_prompt": "" },
      { "id": "C", "text": "Histoire des Premières Nations", "image_prompt": "" },
      { "id": "D", "text": "Sculptures du XIXe siècle", "image_prompt": "" }
    ],
    "correct": 0,
    "transcript_fr": "Bienvenue au Musée des Beaux-Arts de Montréal. Nous vous invitons à découvrir notre nouvelle exposition temporaire 'Regards sur le Québec moderne' qui présente les oeuvres de vingt artistes québécois des années 1950 à 1980. L'exposition est située au deuxième étage, aile nord. L'entrée est gratuite pour les membres et à 15$ pour le grand public. Visites guidées tous les jours à 14 heures. L'exposition se termine le 30 avril prochain. Profitez-en, c'est une collection exceptionnelle!",
    "transcript_en": "Welcome to the Montreal Museum of Fine Arts. We invite you to discover our new temporary exhibition 'Perspectives on Modern Quebec' which presents the works of twenty Quebec artists from 1950 to 1980. The exhibition is located on the second floor, north wing. Admission is free for members and $15 for the general public. Guided tours every day at 2 PM. The exhibition ends April 30th. Take advantage of it, it's an exceptional collection!",
    "points": [
      {
        "point": 1,
        "male_lines": ["Bienvenue au Musée des Beaux-Arts de Montréal."],
        "female_lines": []
      },
      {
        "point": 2,
        "male_lines": ["Nous vous invitons à découvrir notre nouvelle exposition temporaire 'Regards sur le Québec moderne' qui présente les oeuvres de vingt artistes québécois des années 1950 à 1980."],
        "female_lines": []
      },
      {
        "point": 3,
        "male_lines": ["L'exposition est située au deuxième étage, aile nord."],
        "female_lines": []
      },
      {
        "point": 4,
        "male_lines": ["L'entrée est gratuite pour les membres et à 15$ pour le grand public."],
        "female_lines": []
      },
      {
        "point": 5,
        "male_lines": ["Visites guidées tous les jours à 14 heures."],
        "female_lines": []
      },
      {
        "point": 6,
        "male_lines": ["L'exposition se termine le 30 avril prochain."],
        "female_lines": []
      },
      {
        "point": 7,
        "male_lines": ["Profitez-en, c'est une collection exceptionnelle!"],
        "female_lines": []
      },
      {
        "point": 8,
        "male_lines": [],
        "female_lines": []
      },
      {
        "point": 9,
        "male_lines": [],
        "female_lines": []
      },
      {
        "point": 10,
        "male_lines": [],
        "female_lines": []
      }
    ]
  },
  {
    "id": 15,
    "section": "C",
    "theme": "Metro announcement",
    "question": "Quel problème est signalé ?",
    "options": [
      { "id": "A", "text": "Une panne d'électricité", "image_prompt": "" },
      { "id": "B", "text": "Un objet sur les rails", "image_prompt": "" },
      { "id": "C", "text": "Des travaux sur la ligne", "image_prompt": "" },
      { "id": "D", "text": "Une interruption de service", "image_prompt": "" }
    ],
    "correct": 3,
    "transcript_fr": "Chers usagers, en raison d'une interruption de service sur la ligne orange entre les stations Berri-UQAM et Lionel-Groulx, nous vous recommandons d'utiliser la ligne verte comme alternative. Des autobus de remplacement circulent entre ces stations. L'interruption devrait durer environ quarante-cinq minutes. Nous vous prions d'accepter nos excuses pour ce désagrément. Les équipes techniques sont sur place et travaillent à résoudre le problème le plus rapidement possible. Merci de votre patience.",
    "transcript_en": "Dear passengers, due to a service interruption on the orange line between Berri-UQAM and Lionel-Groulx stations, we recommend using the green line as an alternative. Replacement buses are running between these stations. The interruption should last approximately forty-five minutes. Please accept our apologies for this inconvenience. Technical teams are on site and working to resolve the problem as quickly as possible. Thank you for your patience.",
    "points": [
      {
        "point": 1,
        "male_lines": ["Chers usagers, en raison d'une interruption de service sur la ligne orange entre les stations Berri-UQAM et Lionel-Groulx, nous vous recommandons d'utiliser la ligne verte comme alternative."],
        "female_lines": []
      },
      {
        "point": 2,
        "male_lines": ["Des autobus de remplacement circulent entre ces stations."],
        "female_lines": []
      },
      {
        "point": 3,
        "male_lines": ["L'interruption devrait durer environ quarante-cinq minutes."],
        "female_lines": []
      },
      {
        "point": 4,
        "male_lines": ["Nous vous prions d'accepter nos excuses pour ce désagrément."],
        "female_lines": []
      },
      {
        "point": 5,
        "male_lines": ["Les équipes techniques sont sur place et travaillent à résoudre le problème le plus rapidement possible."],
        "female_lines": []
      },
      {
        "point": 6,
        "male_lines": ["Merci de votre patience."],
        "female_lines": []
      },
      {
        "point": 7,
        "male_lines": [],
        "female_lines": []
      },
      {
        "point": 8,
        "male_lines": [],
        "female_lines": []
      },
      {
        "point": 9,
        "male_lines": [],
        "female_lines": []
      },
      {
        "point": 10,
        "male_lines": [],
        "female_lines": []
      }
    ]
  },
  {
    "id": 16,
    "section": "C",
    "theme": "Weather alert",
    "question": "Quel type d'alerte est émis ?",
    "options": [
      { "id": "A", "text": "Alerte de tornade", "image_prompt": "" },
      { "id": "B", "text": "Alerte de verglas", "image_prompt": "" },
      { "id": "C", "text": "Alerte de neige abondante", "image_prompt": "" },
      { "id": "D", "text": "Alerte de chaleur extrême", "image_prompt": "" }
    ],
    "correct": 2,
    "transcript_fr": "Environnement Canada émet une alerte de neige abondante pour la région de Montréal et ses environs. On prévoit de 25 à 35 centimètres de neige entre ce soir et demain midi. Les vents forts causeront de la poudrerie et une visibilité réduite sur les routes. Évitez les déplacements non essentiels. Si vous devez sortir, équipez-vous de pneus d'hiver et prévoyez des délais importants. Les écoles pourraient être fermées demain. Restez à l'écoute des médias pour les mises à jour.",
    "transcript_en": "Environment Canada is issuing a heavy snowfall alert for the Montreal region and surrounding areas. We expect 25 to 35 centimeters of snow between tonight and tomorrow noon. Strong winds will cause blowing snow and reduced visibility on roads. Avoid non-essential travel. If you must go out, equip yourself with winter tires and expect significant delays. Schools may be closed tomorrow. Stay tuned to media for updates.",
    "points": [
      {
        "point": 1,
        "male_lines": ["Environnement Canada émet une alerte de neige abondante pour la région de Montréal et ses environs."],
        "female_lines": []
      },
      {
        "point": 2,
        "male_lines": ["On prévoit de 25 à 35 centimètres de neige entre ce soir et demain midi."],
        "female_lines": []
      },
      {
        "point": 3,
        "male_lines": ["Les vents forts causeront de la poudrerie et une visibilité réduite sur les routes."],
        "female_lines": []
      },
      {
        "point": 4,
        "male_lines": ["Évitez les déplacements non essentiels."],
        "female_lines": []
      },
      {
        "point": 5,
        "male_lines": ["Si vous devez sortir, équipez-vous de pneus d'hiver et prévoyez des délais importants."],
        "female_lines": []
      },
      {
        "point": 6,
        "male_lines": ["Les écoles pourraient être fermées demain."],
        "female_lines": []
      },
      {
        "point": 7,
        "male_lines": ["Restez à l'écoute des médias pour les mises à jour."],
        "female_lines": []
      },
      {
        "point": 8,
        "male_lines": [],
        "female_lines": []
      },
      {
        "point": 9,
        "male_lines": [],
        "female_lines": []
      },
      {
        "point": 10,
        "male_lines": [],
        "female_lines": []
      }
    ]
  },
  {
    "id": 17,
    "section": "D",
    "theme": "Making plans",
    "question": "Quelle est l'intention du premier locuteur ?",
    "options": [
      { "id": "A", "text": "Inviter à un restaurant", "image_prompt": "" },
      { "id": "B", "text": "Proposer une randonnée", "image_prompt": "" },
      { "id": "C", "text": "Demander un service", "image_prompt": "" },
      { "id": "D", "text": "Refuser une invitation", "image_prompt": "" }
    ],
    "correct": 1,
    "transcript_fr": "Marc: Hé Julie, ça te dirait d'aller faire une randonnée au Mont-Royal ce weekend ? Il va faire beau. Julie: Bonne idée! Samedi ou dimanche ? Marc: Je préfère samedi matin, on évitera la foule. Julie: Parfait, on se retrouve à l'entrée principale à 9h ? Marc: D'accord, n'oublie pas tes chaussures de marche. Julie: Pas de souci, à samedi!",
    "transcript_en": "Marc: Hey Julie, would you like to go hiking on Mount Royal this weekend? It's going to be nice weather. Julie: Good idea! Saturday or Sunday? Marc: I prefer Saturday morning, we'll avoid the crowds. Julie: Perfect, shall we meet at the main entrance at 9 AM? Marc: Okay, don't forget your hiking shoes. Julie: No worries, see you Saturday!",
    "points": [
      {
        "point": 1,
        "male_lines": ["Hé Julie, ça te dirait d'aller faire une randonnée au Mont-Royal ce weekend ? Il va faire beau."],
        "female_lines": ["Bonne idée! Samedi ou dimanche ?"]
      },
      {
        "point": 2,
        "male_lines": ["Je préfère samedi matin, on évitera la foule."],
        "female_lines": ["Parfait, on se retrouve à l'entrée principale à 9h ?"]
      },
      {
        "point": 3,
        "male_lines": ["D'accord, n'oublie pas tes chaussures de marche."],
        "female_lines": ["Pas de souci, à samedi!"]
      },
      {
        "point": 4,
        "male_lines": [],
        "female_lines": []
      }
    ]
  },
  {
    "id": 18,
    "section": "D",
    "theme": "Complaint",
    "question": "Quel est le problème évoqué ?",
    "options": [
      { "id": "A", "text": "Un bruit excessif", "image_prompt": "" },
      { "id": "B", "text": "Une fuite d'eau", "image_prompt": "" },
      { "id": "C", "text": "Un chauffage défectueux", "image_prompt": "" },
      { "id": "D", "text": "Une porte bloquée", "image_prompt": "" }
    ],
    "correct": 0,
    "transcript_fr": "Voisine: Monsieur Tremblay, pourriez-vous baisser un peu la musique ? Il est minuit et mes enfants dorment. Monsieur: Oh excusez-moi madame, je ne réalisais pas que c'était si fort. Voisine: C'est la troisième fois cette semaine, ça devient difficile. Monsieur: Vous avez raison, je vais mettre mes écouteurs. Voisine: Merci beaucoup, bonne soirée.",
    "transcript_en": "Neighbor: Mr. Tremblay, could you turn down the music a bit? It's midnight and my children are sleeping. Mr.: Oh excuse me madam, I didn't realize it was so loud. Neighbor: It's the third time this week, it's becoming difficult. Mr.: You're right, I'll put on my headphones. Neighbor: Thank you very much, good evening.",
    "points": [
      {
        "point": 1,
        "male_lines": ["Monsieur Tremblay, pourriez-vous baisser un peu la musique ? Il est minuit et mes enfants dorment."],
        "female_lines": ["Oh excusez-moi madame, je ne réalisais pas que c'était si fort."]
      },
      {
        "point": 2,
        "male_lines": ["C'est la troisième fois cette semaine, ça devient difficile."],
        "female_lines": ["Vous avez raison, je vais mettre mes écouteurs."]
      },
      {
        "point": 3,
        "male_lines": ["Merci beaucoup, bonne soirée."],
        "female_lines": []
      },
      {
        "point": 4,
        "male_lines": [],
        "female_lines": []
      }
    ]
  },
  {
    "id": 19,
    "section": "D",
    "theme": "Job interview",
    "question": "Quelle information le candidat demande-t-il ?",
    "options": [
      { "id": "A", "text": "Le salaire proposé", "image_prompt": "" },
      { "id": "B", "text": "Les heures de travail", "image_prompt": "" },
      { "id": "C", "text": "La date de début", "image_prompt": "" },
      { "id": "D", "text": "Les avantages sociaux", "image_prompt": "" }
    ],
    "correct": 2,
    "transcript_fr": "Employeur: Félicitations, nous aimerions vous offrir le poste de coordonnateur. Candidat: Merci beaucoup, je suis ravi! Quand souhaiteriez-vous que je commence ? Employeur: Idéalement le premier mai, ça vous convient ? Candidat: Oui parfait, j'aurai le temps de donner mon préavis. Employeur: Excellent, nous vous enverrons le contrat la semaine prochaine.",
    "transcript_en": "Employer: Congratulations, we would like to offer you the coordinator position. Candidate: Thank you very much, I'm delighted! When would you like me to start? Employer: Ideally May 1st, does that work for you? Candidate: Yes perfect, I'll have time to give my notice. Employer: Excellent, we'll send you the contract next week.",
    "points": [
      {
        "point": 1,
        "male_lines": ["Félicitations, nous aimerions vous offrir le poste de coordonnateur."],
        "female_lines": ["Merci beaucoup, je suis ravi! Quand souhaiteriez-vous que je commence ?"]
      },
      {
        "point": 2,
        "male_lines": ["Idéalement le premier mai, ça vous convient ?"],
        "female_lines": ["Oui parfait, j'aurai le temps de donner mon préavis."]
      },
      {
        "point": 3,
        "male_lines": ["Excellent, nous vous enverrons le contrat la semaine prochaine."],
        "female_lines": []
      },
      {
        "point": 4,
        "male_lines": [],
        "female_lines": []
      }
    ]
  },
  {
    "id": 20,
    "section": "D",
    "theme": "Technical support",
    "question": "Quelle solution est proposée ?",
    "options": [
      { "id": "A", "text": "Remplacer l'appareil", "image_prompt": "" },
      { "id": "B", "text": "Redémarrer le système", "image_prompt": "" },
      { "id": "C", "text": "Mettre à jour le logiciel", "image_prompt": "" },
      { "id": "D", "text": "Vérifier la connexion", "image_prompt": "" }
    ],
    "correct": 1,
    "transcript_fr": "Technicien: Bonjour, support technique, j'écoute. Cliente: Mon ordinateur est complètement figé, rien ne répond. Technicien: D'accord, maintenez le bouton d'alimentation enfoncé pendant dix secondes pour l'éteindre. Cliente: C'est fait, il s'est éteint. Technicien: Maintenant rallumez-le normalement, le problème devrait être résolu. Cliente: Ça marche, merci beaucoup!",
    "transcript_en": "Technician: Hello, technical support, I'm listening. Client: My computer is completely frozen, nothing is responding. Technician: Okay, hold down the power button for ten seconds to turn it off. Client: Done, it turned off. Technician: Now turn it back on normally, the problem should be resolved. Client: It works, thank you very much!",
    "points": [
      {
        "point": 1,
        "male_lines": ["Bonjour, support technique, j'écoute."],
        "female_lines": ["Mon ordinateur est complètement figé, rien ne répond."]
      },
      {
        "point": 2,
        "male_lines": ["D'accord, maintenez le bouton d'alimentation enfoncé pendant dix secondes pour l'éteindre."],
        "female_lines": ["C'est fait, il s'est éteint."]
      },
      {
        "point": 3,
        "male_lines": ["Maintenant rallumez-le normalement, le problème devrait être résolu."],
        "female_lines": ["Ça marche, merci beaucoup!"]
      },
      {
        "point": 4,
        "male_lines": [],
        "female_lines": []
      }
    ]
  },
  {
    "id": 21,
    "section": "D",
    "theme": "Returning an item",
    "question": "Pourquoi le client retourne-t-il l'article ?",
    "options": [
      { "id": "A", "text": "Il est défectueux", "image_prompt": "" },
      { "id": "B", "text": "La taille ne convient pas", "image_prompt": "" },
      { "id": "C", "text": "Il a changé d'avis", "image_prompt": "" },
      { "id": "D", "text": "Le prix a baissé", "image_prompt": "" }
    ],
    "correct": 1,
    "transcript_fr": "Client: Bonjour, j'aimerais retourner ce manteau. Vendeuse: Bien sûr, quel est le problème ? Client: Je l'ai acheté en taille moyenne mais il est trop grand. Vendeuse: Je vois, avez-vous le ticket de caisse ? Client: Oui, le voici. Vendeuse: Parfait, je peux vous l'échanger contre un small ou vous faire un remboursement.",
    "transcript_en": "Customer: Hello, I would like to return this coat. Saleswoman: Of course, what's the problem? Customer: I bought it in medium but it's too big. Saleswoman: I see, do you have the receipt? Customer: Yes, here it is. Saleswoman: Perfect, I can exchange it for a small or give you a refund.",
    "points": [
      {
        "point": 1,
        "male_lines": ["Bonjour, j'aimerais retourner ce manteau."],
        "female_lines": ["Bien sûr, quel est le problème ?"]
      },
      {
        "point": 2,
        "male_lines": ["Je l'ai acheté en taille moyenne mais il est trop grand."],
        "female_lines": ["Je vois, avez-vous le ticket de caisse ?"]
      },
      {
        "point": 3,
        "male_lines": ["Oui, le voici."],
        "female_lines": ["Parfait, je peux vous l'échanger contre un small ou vous faire un remboursement."]
      },
      {
        "point": 4,
        "male_lines": [],
        "female_lines": []
      }
    ]
  },
  {
    "id": 22,
    "section": "D",
    "theme": "Asking for directions",
    "question": "Où veut aller le touriste ?",
    "options": [
      { "id": "A", "text": "À la gare centrale", "image_prompt": "" },
      { "id": "B", "text": "Au Vieux-Port", "image_prompt": "" },
      { "id": "C", "text": "Au stade olympique", "image_prompt": "" },
      { "id": "D", "text": "Au marché Jean-Talon", "image_prompt": "" }
    ],
    "correct": 3,
    "transcript_fr": "Touriste: Excusez-moi, pourriez-vous m'indiquer le chemin pour le marché Jean-Talon ? Passante: Oui, continuez tout droit sur cette rue jusqu'à la rue Jean-Talon, puis tournez à gauche. Touriste: C'est loin à pied ? Passante: Environ quinze minutes. Vous pouvez aussi prendre le métro, station Jean-Talon. Touriste: Merci beaucoup pour votre aide!",
    "transcript_en": "Tourist: Excuse me, could you tell me the way to Jean-Talon Market? Passerby: Yes, continue straight on this street to Jean-Talon Street, then turn left. Tourist: Is it far to walk? Passerby: About fifteen minutes. You can also take the metro, Jean-Talon station. Tourist: Thank you very much for your help!",
    "points": [
      {
        "point": 1,
        "male_lines": ["Excusez-moi, pourriez-vous m'indiquer le chemin pour le marché Jean-Talon ?"],
        "female_lines": ["Oui, continuez tout droit sur cette rue jusqu'à la rue Jean-Talon, puis tournez à gauche."]
      },
      {
        "point": 2,
        "male_lines": ["C'est loin à pied ?"],
        "female_lines": ["Environ quinze minutes. Vous pouvez aussi prendre le métro, station Jean-Talon."]
      },
      {
        "point": 3,
        "male_lines": ["Merci beaucoup pour votre aide!"],
        "female_lines": []
      },
      {
        "point": 4,
        "male_lines": [],
        "female_lines": []
      }
    ]
  },
  {
    "id": 23,
    "section": "E",
    "theme": "Radio interview - Environment",
    "question": "Quelle est la principale préoccupation de l'invité ?",
    "options": [
      { "id": "A", "text": "La pollution de l'air", "image_prompt": "" },
      { "id": "B", "text": "La déforestation", "image_prompt": "" },
      { "id": "C", "text": "Le réchauffement climatique", "image_prompt": "" },
      { "id": "D", "text": "La gestion des déchets", "image_prompt": "" }
    ],
    "correct": 2,
    "transcript_fr": "Animateur: Bienvenue à notre émission, nous avons avec nous le Dr. Bernard Lavallée, environnementaliste. Docteur: Merci d'être ici. Animateur: Quel est le plus grand défi environnemental actuellement ? Docteur: Sans doute le réchauffement climatique, ses effets sont visibles partout au Québec. Animateur: Quelles solutions proposez-vous ? Docteur: Nous devons réduire nos émissions de gaz à effet de serre de 50% d'ici 2030.",
    "transcript_en": "Host: Welcome to our show, we have with us Dr. Bernard Lavallée, environmentalist. Doctor: Thank you for having me. Host: What is the biggest environmental challenge currently? Doctor: Undoubtedly climate change, its effects are visible everywhere in Quebec. Host: What solutions do you propose? Doctor: We must reduce our greenhouse gas emissions by 50% by 2030.",
    "points": [
      {
        "point": 1,
        "male_lines": ["Bienvenue à notre émission, nous avons avec nous le Dr. Bernard Lavallée, environnementaliste."],
        "female_lines": ["Merci d'être ici."]
      },
      {
        "point": 2,
        "male_lines": ["Quel est le plus grand défi environnemental actuellement ?"],
        "female_lines": ["Sans doute le réchauffement climatique, ses effets sont visibles partout au Québec."]
      },
      {
        "point": 3,
        "male_lines": ["Quelles solutions proposez-vous ?"],
        "female_lines": ["Nous devons réduire nos émissions de gaz à effet de serre de 50% d'ici 2030."]
      },
      {
        "point": 4,
        "male_lines": [],
        "female_lines": []
      }
    ]
  },
  {
    "id": 24,
    "section": "E",
    "theme": "Radio interview - Technology",
    "question": "Quel sujet est discuté ?",
    "options": [
      { "id": "A", "text": "L'intelligence artificielle", "image_prompt": "" },
      { "id": "B", "text": "Les voitures électriques", "image_prompt": "" },
      { "id": "C", "text": "La réalité virtuelle", "image_prompt": "" },
      { "id": "D", "text": "Les smartphones 5G", "image_prompt": "" }
    ],
    "correct": 0,
    "transcript_fr": "Journaliste: Aujourd'hui nous parlons de l'intelligence artificielle avec Marie Chen, experte en technologie. Experte: Bonjour à tous. Journaliste: L'IA va-t-elle remplacer les emplois ? Experte: Certaines tâches oui, mais elle créera aussi de nouveaux métiers. Journaliste: Quels secteurs sont concernés ? Experte: Principalement la santé, la finance et le transport. Il faut se préparer à cette transition.",
    "transcript_en": "Journalist: Today we're talking about artificial intelligence with Marie Chen, technology expert. Expert: Hello everyone. Journalist: Will AI replace jobs? Expert: Some tasks yes, but it will also create new professions. Journalist: Which sectors are concerned? Expert: Mainly health, finance, and transportation. We must prepare for this transition.",
    "points": [
      {
        "point": 1,
        "male_lines": ["Aujourd'hui nous parlons de l'intelligence artificielle avec Marie Chen, experte en technologie."],
        "female_lines": ["Bonjour à tous."]
      },
      {
        "point": 2,
        "male_lines": ["L'IA va-t-elle remplacer les emplois ?"],
        "female_lines": ["Certaines tâches oui, mais elle créera aussi de nouveaux métiers."]
      },
      {
        "point": 3,
        "male_lines": ["Quels secteurs sont concernés ?"],
        "female_lines": ["Principalement la santé, la finance et le transport. Il faut se préparer à cette transition."]
      },
      {
        "point": 4,
        "male_lines": [],
        "female_lines": []
      }
    ]
  },
  {
    "id": 25,
    "section": "E",
    "theme": "Radio interview - Health",
    "question": "Quel conseil l'experte donne-t-elle ?",
    "options": [
      { "id": "A", "text": "Dormir huit heures par nuit", "image_prompt": "" },
      { "id": "B", "text": "Boire plus d'eau", "image_prompt": "" },
      { "id": "C", "text": "Faire trente minutes d'exercice par jour", "image_prompt": "" },
      { "id": "D", "text": "Manger cinq fruits et légumes", "image_prompt": "" }
    ],
    "correct": 2,
    "transcript_fr": "Animateur: Notre nutritionniste Sophie Martin est avec nous. Sophie: Bonjour! Animateur: Quel est votre conseil santé numéro un ? Sophie: Bouger! Trente minutes d'activité physique par jour minimum. Animateur: Même une simple marche ? Sophie: Absolument, la marche rapide est excellente pour le coeur. Animateur: Et pour ceux qui n'ont pas le temps ? Sophie: Prendre les escaliers, marcher pendant les pauses, tout compte!",
    "transcript_en": "Host: Our nutritionist Sophie Martin is with us. Sophie: Hello! Host: What is your number one health advice? Sophie: Move! Thirty minutes of physical activity per day minimum. Host: Even a simple walk? Sophie: Absolutely, brisk walking is excellent for the heart. Host: And for those who don't have time? Sophie: Take the stairs, walk during breaks, everything counts!",
    "points": [
      {
        "point": 1,
        "male_lines": ["Notre nutritionniste Sophie Martin est avec nous."],
        "female_lines": ["Bonjour!"]
      },
      {
        "point": 2,
        "male_lines": ["Quel est votre conseil santé numéro un ?"],
        "female_lines": ["Bouger! Trente minutes d'activité physique par jour minimum."]
      },
      {
        "point": 3,
        "male_lines": ["Même une simple marche ?"],
        "female_lines": ["Absolument, la marche rapide est excellente pour le coeur."]
      },
      {
        "point": 4,
        "male_lines": ["Et pour ceux qui n'ont pas le temps ?"],
        "female_lines": ["Prendre les escaliers, marcher pendant les pauses, tout compte!"]
      }
    ]
  },
  {
    "id": 26,
    "section": "E",
    "theme": "Radio interview - Culture",
    "question": "Quel événement culturel est présenté ?",
    "options": [
      { "id": "A", "text": "Un festival de jazz", "image_prompt": "" },
      { "id": "B", "text": "Une exposition de cinéma", "image_prompt": "" },
      { "id": "C", "text": "Un salon du livre", "image_prompt": "" },
      { "id": "D", "text": "Une biennale d'art", "image_prompt": "" }
    ],
    "correct": 0,
    "transcript_fr": "Présentateur: Le Festival International de Jazz de Montréal commence demain. Organisatrice: Oui, trois semaines de musique! Présentateur: Quels sont les têtes d'affiche ? Organisatrice: Cette année nous avons Diana Krall et Wynton Marsalis. Présentateur: Où peut-on acheter des billets ? Organisatrice: Sur notre site web ou directement sur place au Quartier des spectacles.",
    "transcript_en": "Presenter: The Montreal International Jazz Festival starts tomorrow. Organizer: Yes, three weeks of music! Presenter: Who are the headliners? Organizer: This year we have Diana Krall and Wynton Marsalis. Presenter: Where can we buy tickets? Organizer: On our website or directly on site at the Quartier des spectacles.",
    "points": [
      {
        "point": 1,
        "male_lines": ["Le Festival International de Jazz de Montréal commence demain."],
        "female_lines": ["Oui, trois semaines de musique!"]
      },
      {
        "point": 2,
        "male_lines": ["Quels sont les têtes d'affiche ?"],
        "female_lines": ["Cette année nous avons Diana Krall et Wynton Marsalis."]
      },
      {
        "point": 3,
        "male_lines": ["Où peut-on acheter des billets ?"],
        "female_lines": ["Sur notre site web ou directement sur place au Quartier des spectacles."]
      },
      {
        "point": 4,
        "male_lines": [],
        "female_lines": []
      }
    ]
  },
  {
    "id": 27,
    "section": "F",
    "theme": "Housing debate",
    "question": "Quel est le sujet principal de la discussion ?",
    "options": [
      { "id": "A", "text": "Les loyers trop élevés", "image_prompt": "" },
      { "id": "B", "text": "La pénurie de logements", "image_prompt": "" },
      { "id": "C", "text": "Les quartiers gentrifiés", "image_prompt": "" },
      { "id": "D", "text": "La qualité de la construction", "image_prompt": "" }
    ],
    "correct": 0,
    "transcript_fr": "Pierre: Tu as vu les nouveaux loyers dans le Plateau ? C'est devenu impossible! Marie: Je sais, mon propriétaire veut augmenter mon loyer de 20%. Pierre: C'est illégal non ? Marie: Malheureusement non, il respecte la limite légale. Pierre: Il faut que le gouvernement intervienne. Marie: Absolument, les jeunes ne peuvent plus se permettre de vivre en ville.",
    "transcript_en": "Pierre: Did you see the new rents in the Plateau? It's become impossible! Marie: I know, my landlord wants to increase my rent by 20%. Pierre: That's illegal, no? Marie: Unfortunately no, he's respecting the legal limit. Pierre: The government needs to intervene. Marie: Absolutely, young people can no longer afford to live in the city.",
    "points": [
      {
        "point": 1,
        "male_lines": ["Tu as vu les nouveaux loyers dans le Plateau ? C'est devenu impossible!"],
        "female_lines": ["Je sais, mon propriétaire veut augmenter mon loyer de 20%."]
      },
      {
        "point": 2,
        "male_lines": ["C'est illégal non ?"],
        "female_lines": ["Malheureusement non, il respecte la limite légale."]
      },
      {
        "point": 3,
        "male_lines": ["Il faut que le gouvernement intervienne."],
        "female_lines": ["Absolument, les jeunes ne peuvent plus se permettre de vivre en ville."]
      },
      {
        "point": 4,
        "male_lines": [],
        "female_lines": []
      }
    ]
  },
  {
    "id": 28,
    "section": "F",
    "theme": "Transport debate",
    "question": "Quelle solution les locuteurs préfèrent-ils ?",
    "options": [
      { "id": "A", "text": "Plus d'autobus", "image_prompt": "" },
      { "id": "B", "text": "Un tramway", "image_prompt": "" },
      { "id": "C", "text": "Des pistes cyclables", "image_prompt": "" },
      { "id": "D", "text": "Le télétravail", "image_prompt": "" }
    ],
    "correct": 2,
    "transcript_fr": "Luc: Le trafic est horrible tous les matins sur le pont. Julie: Oui, et le métro est bondé. Luc: Il faudrait plus de pistes cyclables sécurisées. Julie: Excellente idée! Je prendrais mon vélo tous les jours. Luc: Moi aussi, mais j'ai peur des voitures actuellement. Julie: Avec des barrières physiques, ce serait parfait. Luc: Écrivons à la mairie pour suggérer ça.",
    "transcript_en": "Luc: Traffic is horrible every morning on the bridge. Julie: Yes, and the metro is packed. Luc: We need more secure bike lanes. Julie: Excellent idea! I would bike every day. Luc: Me too, but I'm afraid of cars currently. Julie: With physical barriers, it would be perfect. Luc: Let's write to the city hall to suggest that.",
    "points": [
      {
        "point": 1,
        "male_lines": ["Le trafic est horrible tous les matins sur le pont."],
        "female_lines": ["Oui, et le métro est bondé."]
      },
      {
        "point": 2,
        "male_lines": ["Il faudrait plus de pistes cyclables sécurisées."],
        "female_lines": ["Excellente idée! Je prendrais mon vélo tous les jours."]
      },
      {
        "point": 3,
        "male_lines": ["Moi aussi, mais j'ai peur des voitures actuellement."],
        "female_lines": ["Avec des barrières physiques, ce serait parfait."]
      },
      {
        "point": 4,
        "male_lines": ["Écrivons à la mairie pour suggérer ça."],
        "female_lines": []
      }
    ]
  },
  {
    "id": 29,
    "section": "F",
    "theme": "Education debate",
    "question": "Quel changement éducatif est discuté ?",
    "options": [
      { "id": "A", "text": "L'interdiction des devoirs", "image_prompt": "" },
      { "id": "B", "text": "L'école à la maison", "image_prompt": "" },
      { "id": "C", "text": "Les cours en ligne", "image_prompt": "" },
      { "id": "D", "text": "L'uniforme scolaire", "image_prompt": "" }
    ],
    "correct": 2,
    "transcript_fr": "Professeur: Les cours en ligne ont changé notre façon d'enseigner. Parent: Oui, mais est-ce aussi efficace ? Professeur: Pour certains élèves oui, pour d'autres non. Parent: Mon fils a du mal à se concentrer devant l'écran. Professeur: C'est un défi. Nous devons trouver un équilibre entre présentiel et distanciel. Parent: Je suis d'accord, le contact humain reste essentiel.",
    "transcript_en": "Teacher: Online classes have changed our way of teaching. Parent: Yes, but is it as effective? Teacher: For some students yes, for others no. Parent: My son has trouble concentrating in front of the screen. Teacher: It's a challenge. We must find a balance between in-person and remote learning. Parent: I agree, human contact remains essential.",
    "points": [
      {
        "point": 1,
        "male_lines": ["Les cours en ligne ont changé notre façon d'enseigner."],
        "female_lines": ["Oui, mais est-ce aussi efficace ?"]
      },
      {
        "point": 2,
        "male_lines": ["Pour certains élèves oui, pour d'autres non."],
        "female_lines": ["Mon fils a du mal à se concentrer devant l'écran."]
      },
      {
        "point": 3,
        "male_lines": ["C'est un défi. Nous devons trouver un équilibre entre présentiel et distanciel."],
        "female_lines": ["Je suis d'accord, le contact humain reste essentiel."]
      },
      {
        "point": 4,
        "male_lines": [],
        "female_lines": []
      }
    ]
  },
  {
    "id": 30,
    "section": "F",
    "theme": "Work-life balance",
    "question": "Quel est l'avis des locuteurs sur le télétravail ?",
    "options": [
      { "id": "A", "text": "Ils sont totalement contre", "image_prompt": "" },
      { "id": "B", "text": "Ils préfèrent le mixte", "image_prompt": "" },
      { "id": "C", "text": "Ils veulent 100% à distance", "image_prompt": "" },
      { "id": "D", "text": "Ils n'ont pas d'opinion", "image_prompt": "" }
    ],
    "correct": 1,
    "transcript_fr": "Thomas: Le télétravail complet me manque de social. Claire: Et le bureau tous les jours, c'est épuisant avec les transports. Thomas: Exactement, je préfère trois jours à la maison, deux au bureau. Claire: C'est l'idéal! On garde la flexibilité et les contacts. Thomas: Mon patron refuse encore cette formule. Claire: Les mentalités changent lentement mais ça va évoluer.",
    "transcript_en": "Thomas: Full remote work lacks social interaction for me. Claire: And the office every day is exhausting with the commute. Thomas: Exactly, I prefer three days at home, two at the office. Claire: That's ideal! We keep flexibility and contacts. Thomas: My boss still refuses this formula. Claire: Mindsets are changing slowly but it will evolve.",
    "points": [
      {
        "point": 1,
        "male_lines": ["Le télétravail complet me manque de social."],
        "female_lines": ["Et le bureau tous les jours, c'est épuisant avec les transports."]
      },
      {
        "point": 2,
        "male_lines": ["Exactement, je préfère trois jours à la maison, deux au bureau."],
        "female_lines": ["C'est l'idéal! On garde la flexibilité et les contacts."]
      },
      {
        "point": 3,
        "male_lines": ["Mon patron refuse encore cette formule."],
        "female_lines": ["Les mentalités changent lentement mais ça va évoluer."]
      },
      {
        "point": 4,
        "male_lines": [],
        "female_lines": []
      }
    ]
  },
  {
    "id": 31,
    "section": "G",
    "theme": "Immigration policy debate",
    "question": "Quel est l'argument principal défendu dans cette discussion ?",
    "options": [
      { "id": "A", "text": "Il faut réduire l'immigration", "image_prompt": "" },
      { "id": "B", "text": "L'immigration est nécessaire pour l'économie", "image_prompt": "" },
      { "id": "C", "text": "Les immigrants doivent apprendre le français plus vite", "image_prompt": "" },
      { "id": "D", "text": "Le processus d'immigration est trop complexe", "image_prompt": "" }
    ],
    "correct": 1,
    "transcript_fr": "Modérateur: Bienvenue à notre débat sur l'immigration au Québec. Notre première intervenante est madame Dubois, économiste. Dubois: Merci. Les données montrent clairement que l'immigration est essentielle pour notre croissance économique. Modérateur: Monsieur Gagnon, vous êtes critique ? Gagnon: Je ne nie pas les bénéfices économiques, mais je m'inquiète de l'intégration linguistique. Dubois: C'est un point valide, mais nos programmes de francisation fonctionnent bien. Gagnon: Les délais d'attente sont trop longs pour les cours. Dubois: Investissons davantage alors, plutôt que de réduire les seuils. Modérateur: Madame Tremblay, votre avis ? Tremblay: Je suis d'accord avec madame Dubois. Mon entreprise recrute 30% d'immigrants, sans eux on fermerait. Gagnon: Mais la pression sur les logements ? Dubois: Encore une question d'investissement public, pas d'immigration. Tremblay: Exactement, construisons plus plutôt que de fermer les frontières. Modérateur: Dernier mot ? Gagnon: Je reste prudent mais je comprends vos arguments économiques.",
    "transcript_en": "Moderator: Welcome to our debate on immigration in Quebec. Our first speaker is Mrs. Dubois, economist. Dubois: Thank you. Data clearly shows that immigration is essential for our economic growth. Moderator: Mr. Gagnon, you are critical? Gagnon: I don't deny the economic benefits, but I worry about language integration. Dubois: That's a valid point, but our francization programs work well. Gagnon: The waiting times for classes are too long. Dubois: Let's invest more then, rather than reducing thresholds. Moderator: Mrs. Tremblay, your opinion? Tremblay: I agree with Mrs. Dubois. My company recruits 30% immigrants, without them we would close. Gagnon: But the pressure on housing? Dubois: Again a question of public investment, not immigration. Tremblay: Exactly, let's build more rather than closing borders. Moderator: Final word? Gagnon: I remain cautious but I understand your economic arguments.",
    "points": [
      {
        "point": 1,
        "male_lines": ["Bienvenue à notre débat sur l'immigration au Québec. Notre première intervenante est madame Dubois, économiste."],
        "female_lines": ["Merci. Les données montrent clairement que l'immigration est essentielle pour notre croissance économique."]
      },
      {
        "point": 2,
        "male_lines": ["Monsieur Gagnon, vous êtes critique ?"],
        "female_lines": ["Je ne nie pas les bénéfices économiques, mais je m'inquiète de l'intégration linguistique."]
      },
      {
        "point": 3,
        "male_lines": ["C'est un point valide, mais nos programmes de francisation fonctionnent bien."],
        "female_lines": ["Les délais d'attente sont trop longs pour les cours."]
      },
      {
        "point": 4,
        "male_lines": ["Investissons davantage alors, plutôt que de réduire les seuils."],
        "female_lines": ["Madame Tremblay, votre avis ?"]
      },
      {
        "point": 5,
        "male_lines": ["Je suis d'accord avec madame Dubois. Mon entreprise recrute 30% d'immigrants, sans eux on fermerait."],
        "female_lines": ["Mais la pression sur les logements ?"]
      },
      {
        "point": 6,
        "male_lines": ["Encore une question d'investissement public, pas d'immigration."],
        "female_lines": ["Exactement, construisons plus plutôt que de fermer les frontières."]
      },
      {
        "point": 7,
        "male_lines": ["Dernier mot ?"],
        "female_lines": ["Je reste prudent mais je comprends vos arguments économiques."]
      },
      {
        "point": 8,
        "male_lines": [],
        "female_lines": []
      },
      {
        "point": 9,
        "male_lines": [],
        "female_lines": []
      },
      {
        "point": 10,
        "male_lines": [],
        "female_lines": []
      }
    ]
  },
  {
    "id": 32,
    "section": "G",
    "theme": "Climate change solutions",
    "question": "Quelle solution est privilégiée par les intervenants ?",
    "options": [
      { "id": "A", "text": "L'énergie nucléaire", "image_prompt": "" },
      { "id": "B", "text": "Les énergies renouvelables", "image_prompt": "" },
      { "id": "C", "text": "La taxe carbone", "image_prompt": "" },
      { "id": "D", "text": "Les transports en commun", "image_prompt": "" }
    ],
    "correct": 1,
    "transcript_fr": "Journaliste: Le Québec doit-il investir davantage dans les énergies vertes ? Expert: Absolument, c'est notre avenir. Notre potentiel hydroélectrique est déjà excellent mais nous devons ajouter l'éolien et le solaire. Journaliste: Le nucléaire n'est pas une option ? Expert: Trop coûteux et risqué pour notre contexte. Journaliste: Et la taxe carbone ? Expert: Nécessaire mais insuffisante seule. Journaliste: Quelle priorité alors ? Expert: La transition énergétique massive dès maintenant. Journaliste: Les entreprises suivront ? Expert: Elles n'auront pas le choix avec les réglementations. Journaliste: Le coût pour les contribuables ? Expert: Investir maintenant coûte moins cher que réparer plus tard. Journaliste: Un message final ? Expert: Agissons avant qu'il ne soit trop tard pour nos enfants.",
    "transcript_en": "Journalist: Should Quebec invest more in green energy? Expert: Absolutely, it's our future. Our hydroelectric potential is already excellent but we must add wind and solar. Journalist: Isn't nuclear an option? Expert: Too expensive and risky for our context. Journalist: And the carbon tax? Expert: Necessary but insufficient alone. Journalist: What priority then? Expert: Massive energy transition starting now. Journalist: Will companies follow? Expert: They won't have a choice with regulations. Journalist: The cost for taxpayers? Expert: Investing now costs less than repairing later. Journalist: A final message? Expert: Let's act before it's too late for our children.",
    "points": [
      {
        "point": 1,
        "male_lines": ["Le Québec doit-il investir davantage dans les énergies vertes ?"],
        "female_lines": ["Absolument, c'est notre avenir. Notre potentiel hydroélectrique est déjà excellent mais nous devons ajouter l'éolien et le solaire."]
      },
      {
        "point": 2,
        "male_lines": ["Le nucléaire n'est pas une option ?"],
        "female_lines": ["Trop coûteux et risqué pour notre contexte."]
      },
      {
        "point": 3,
        "male_lines": ["Et la taxe carbone ?"],
        "female_lines": ["Nécessaire mais insuffisante seule."]
      },
      {
        "point": 4,
        "male_lines": ["Quelle priorité alors ?"],
        "female_lines": ["La transition énergétique massive dès maintenant."]
      },
      {
        "point": 5,
        "male_lines": ["Les entreprises suivront ?"],
        "female_lines": ["Elles n'auront pas le choix avec les réglementations."]
      },
      {
        "point": 6,
        "male_lines": ["Le coût pour les contribuables ?"],
        "female_lines": ["Investir maintenant coûte moins cher que réparer plus tard."]
      },
      {
        "point": 7,
        "male_lines": ["Un message final ?"],
        "female_lines": ["Agissons avant qu'il ne soit trop tard pour nos enfants."]
      },
      {
        "point": 8,
        "male_lines": [],
        "female_lines": []
      },
      {
        "point": 9,
        "male_lines": [],
        "female_lines": []
      },
      {
        "point": 10,
        "male_lines": [],
        "female_lines": []
      }
    ]
  },
  {
    "id": 33,
    "section": "G",
    "theme": "Healthcare system challenges",
    "question": "Quel est le principal débat concernant la santé ?",
    "options": [
      { "id": "A", "text": "Le manque de médecins", "image_prompt": "" },
      { "id": "B", "text": "La privatisation partielle", "image_prompt": "" },
      { "id": "C", "text": "Les listes d'attente", "image_prompt": "" },
      { "id": "D", "text": "Le vieillissement de la population", "image_prompt": "" }
    ],
    "correct": 1,
    "transcript_fr": "Animateur: Le système de santé québécois est en crise. Docteur Roy, que proposez-vous ? Roy: Nous devons permettre une privatisation encadrée pour réduire les attentes. Animateur: Madame Lefebvre, vous êtes contre ? Lefebvre: Totalement. Cela créera un système à deux vitesses. Roy: Mais les patients attendent deux ans pour une opération! Lefebvre: Investissons dans le public plutôt. Roy: Nous n'avons pas assez de ressources. Lefebvre: Si nous arrêtions de gaspiller dans l'administration. Animateur: Un compromis possible ? Roy: Le privé pourrait soulager le public sans remplacer. Lefebvre: C'est une pente glissante dangereuse. Animateur: Merci à tous les deux pour ce débat.",
    "transcript_en": "Host: The Quebec health system is in crisis. Dr. Roy, what do you propose? Roy: We must allow regulated privatization to reduce wait times. Host: Mrs. Lefebvre, you are against? Lefebvre: Totally. This will create a two-tier system. Roy: But patients wait two years for surgery! Lefebvre: Let's invest in the public system instead. Roy: We don't have enough resources. Lefebvre: If we stopped wasting on administration. Host: A possible compromise? Roy: The private sector could relieve the public without replacing it. Lefebvre: It's a dangerous slippery slope. Host: Thank you both for this debate.",
    "points": [
      {
        "point": 1,
        "male_lines": ["Le système de santé québécois est en crise. Docteur Roy, que proposez-vous ?"],
        "female_lines": ["Nous devons permettre une privatisation encadrée pour réduire les attentes."]
      },
      {
        "point": 2,
        "male_lines": ["Madame Lefebvre, vous êtes contre ?"],
        "female_lines": ["Totalement. Cela créera un système à deux vitesses."]
      },
      {
        "point": 3,
        "male_lines": ["Mais les patients attendent deux ans pour une opération!"],
        "female_lines": ["Investissons dans le public plutôt."]
      },
      {
        "point": 4,
        "male_lines": ["Nous n'avons pas assez de ressources."],
        "female_lines": ["Si nous arrêtions de gaspiller dans l'administration."]
      },
      {
        "point": 5,
        "male_lines": ["Un compromis possible ?"],
        "female_lines": ["Le privé pourrait soulager le public sans remplacer."]
      },
      {
        "point": 6,
        "male_lines": ["C'est une pente glissante dangereuse."],
        "female_lines": ["Merci à tous les deux pour ce débat."]
      },
      {
        "point": 7,
        "male_lines": [],
        "female_lines": []
      },
      {
        "point": 8,
        "male_lines": [],
        "female_lines": []
      },
      {
        "point": 9,
        "male_lines": [],
        "female_lines": []
      },
      {
        "point": 10,
        "male_lines": [],
        "female_lines": []
      }
    ]
  },
  {
    "id": 34,
    "section": "G",
    "theme": "Indigenous reconciliation",
    "question": "Quelle mesure est discutée pour la réconciliation ?",
    "options": [
      { "id": "A", "text": "Des excuses officielles", "image_prompt": "" },
      { "id": "B", "text": "L'enseignement des langues autochtones", "image_prompt": "" },
      { "id": "C", "text": "La restitution des terres", "image_prompt": "" },
      { "id": "D", "text": "Compensation financière", "image_prompt": "" }
    ],
    "correct": 1,
    "transcript_fr": "Présentateur: Comment avancer vers la réconciliation avec les peuples autochtones ? Chef: Nous devons commencer par l'éducation. Nos langues doivent être enseignées dans les écoles. Présentateur: Dans toutes les écoles ? Chef: Au moins comme option partout au Québec. Présentateur: Madame le ministre, c'est réaliste ? Ministre: Nous travaillons déjà sur des programmes pilotes. Chef: C'est trop lent, nos aînés meurent sans transmettre leurs connaissances. Ministre: Je comprends l'urgence. Nous allons accélérer. Présentateur: Et les terres ? Chef: La question territoriale est cruciale mais l'éducation crée le respect. Ministre: Je suis d'accord sur l'importance de la culture. Présentateur: Des engagements concrets alors ? Ministre: 50 nouveaux programmes d'ici 2025. Chef: C'est un début encourageant.",
    "transcript_en": "Presenter: How to move forward with reconciliation with Indigenous peoples? Chief: We must start with education. Our languages must be taught in schools. Presenter: In all schools? Chief: At least as an option everywhere in Quebec. Presenter: Mrs. Minister, is this realistic? Minister: We are already working on pilot programs. Chief: It's too slow, our elders are dying without transmitting their knowledge. Minister: I understand the urgency. We will accelerate. Presenter: And the lands? Chief: The territorial question is crucial but education creates respect. Minister: I agree on the importance of culture. Presenter: Concrete commitments then? Minister: 50 new programs by 2025. Chief: It's an encouraging start.",
    "points": [
      {
        "point": 1,
        "male_lines": ["Comment avancer vers la réconciliation avec les peuples autochtones ?"],
        "female_lines": ["Nous devons commencer par l'éducation. Nos langues doivent être enseignées dans les écoles."]
      },
      {
        "point": 2,
        "male_lines": ["Dans toutes les écoles ?"],
        "female_lines": ["Au moins comme option partout au Québec."]
      },
      {
        "point": 3,
        "male_lines": ["Madame le ministre, c'est réaliste ?"],
        "female_lines": ["Nous travaillons déjà sur des programmes pilotes."]
      },
      {
        "point": 4,
        "male_lines": ["C'est trop lent, nos aînés meurent sans transmettre leurs connaissances."],
        "female_lines": ["Je comprends l'urgence. Nous allons accélérer."]
      },
      {
        "point": 5,
        "male_lines": ["Et les terres ?"],
        "female_lines": ["La question territoriale est cruciale mais l'éducation crée le respect."]
      },
      {
        "point": 6,
        "male_lines": ["Je suis d'accord sur l'importance de la culture."],
        "female_lines": ["Des engagements concrets alors ?"]
      },
      {
        "point": 7,
        "male_lines": ["50 nouveaux programmes d'ici 2025."],
        "female_lines": ["C'est un début encourageant."]
      },
      {
        "point": 8,
        "male_lines": [],
        "female_lines": []
      },
      {
        "point": 9,
        "male_lines": [],
        "female_lines": []
      },
      {
        "point": 10,
        "male_lines": [],
        "female_lines": []
      }
    ]
  },
  {
    "id": 35,
    "section": "G",
    "theme": "Digital privacy",
    "question": "Quelle est la position des locuteurs sur la vie privée numérique ?",
    "options": [
      { "id": "A", "text": "La sécurité prime sur la vie privée", "image_prompt": "" },
      { "id": "B", "text": "Il faut plus de réglementation", "image_prompt": "" },
      { "id": "C", "text": "Les citoyens doivent se protéger eux-mêmes", "image_prompt": "" },
      { "id": "D", "text": "Les entreprises sont responsables", "image_prompt": "" }
    ],
    "correct": 1,
    "transcript_fr": "Journaliste: Nos données personnelles sont-elles suffisamment protégées ? Avocat: Non, la loi est obsolète face aux géants du web. Journaliste: Que proposez-vous ? Avocat: Une réglementation stricte comme en Europe avec le RGPD. Journaliste: Madame, vous représentez une entreprise tech ? Tech: Nous prenons déjà la protection au sérieux. Avocat: Pas assez, les fuites sont fréquentes. Tech: La réglementation excessive freine l'innovation. Avocat: La vie privée des citoyens est plus importante. Journaliste: Un équilibre possible ? Avocat: Oui, mais il faut des sanctions dissuasives. Tech: Nous sommes ouverts au dialogue. Journaliste: Le gouvernement doit-il intervenir ? Avocat: Absolument et rapidement. Tech: Avec modération.",
    "transcript_en": "Journalist: Are our personal data sufficiently protected? Lawyer: No, the law is obsolete compared to web giants. Journalist: What do you propose? Lawyer: Strict regulation like in Europe with GDPR. Journalist: Madam, you represent a tech company? Tech: We already take protection seriously. Lawyer: Not enough, leaks are frequent. Tech: Excessive regulation hinders innovation. Lawyer: Citizens' privacy is more important. Journalist: A possible balance? Lawyer: Yes, but we need deterrent sanctions. Tech: We are open to dialogue. Journalist: Should the government intervene? Lawyer: Absolutely and quickly. Tech: With moderation.",
    "points": [
      {
        "point": 1,
        "male_lines": ["Nos données personnelles sont-elles suffisamment protégées ?"],
        "female_lines": ["Non, la loi est obsolète face aux géants du web."]
      },
      {
        "point": 2,
        "male_lines": ["Que proposez-vous ?"],
        "female_lines": ["Une réglementation stricte comme en Europe avec le RGPD."]
      },
      {
        "point": 3,
        "male_lines": ["Madame, vous représentez une entreprise tech ?"],
        "female_lines": ["Nous prenons déjà la protection au sérieux."]
      },
      {
        "point": 4,
        "male_lines": ["Pas assez, les fuites sont fréquentes."],
        "female_lines": ["La réglementation excessive freine l'innovation."]
      },
      {
        "point": 5,
        "male_lines": ["La vie privée des citoyens est plus importante."],
        "female_lines": ["Un équilibre possible ?"]
      },
      {
        "point": 6,
        "male_lines": ["Oui, mais il faut des sanctions dissuasives."],
        "female_lines": ["Nous sommes ouverts au dialogue."]
      },
      {
        "point": 7,
        "male_lines": ["Le gouvernement doit-il intervenir ?"],
        "female_lines": ["Absolument et rapidement."]
      },
      {
        "point": 8,
        "male_lines": ["Avec modération."],
        "female_lines": []
      },
      {
        "point": 9,
        "male_lines": [],
        "female_lines": []
      },
      {
        "point": 10,
        "male_lines": [],
        "female_lines": []
      }
    ]
  },
  {
    "id": 36,
    "section": "H",
    "theme": "Philosophy of language",
    "question": "Quel concept philosophique est discuté ?",
    "options": [
      { "id": "A", "text": "Le déterminisme linguistique", "image_prompt": "" },
      { "id": "B", "text": "La relativité culturelle", "image_prompt": "" },
      { "id": "C", "text": "L'innéisme", "image_prompt": "" },
      { "id": "D", "text": "L'existentialisme", "image_prompt": "" }
    ],
    "correct": 0,
    "transcript_fr": "Conférencier: La thèse de Sapir-Whorf suggère que la langue façonne notre pensée. Auditeur: Vous voulez dire que nous ne pouvons pas penser hors de notre langue ? Conférencier: C'est une version forte. La version faible dit seulement que la langue influence la perception. Auditeur: Quel exemple concret ? Conférencier: Les Inuits auraient plusieurs mots pour la neige, percevant ainsi des nuances que nous ne voyons pas. Auditeur: Cela a-t-il été prouvé ? Conférencier: C'est débattu, mais l'idée reste fascinante. Auditeur: Et pour le bilinguisme ? Conférencier: Les bilingues développent souvent une flexibilité cognitive supérieure. Auditeur: Donc apprendre une langue change notre cerveau ? Conférencier: Exactement, cela crée de nouvelles connexions neuronales. Auditeur: Implications pour l'éducation ? Conférencier: L'apprentissage précoce des langues devrait être une priorité nationale. Auditeur: Merci pour ces éclaircissements.",
    "transcript_en": "Speaker: The Sapir-Whorf thesis suggests that language shapes our thought. Listener: You mean we cannot think outside our language? Speaker: That's the strong version. The weak version only says language influences perception. Listener: What concrete example? Speaker: Inuits supposedly have several words for snow, thus perceiving nuances we don't see. Listener: Has this been proven? Speaker: It's debated, but the idea remains fascinating. Listener: And for bilingualism? Speaker: Bilinguals often develop superior cognitive flexibility. Listener: So learning a language changes our brain? Speaker: Exactly, it creates new neural connections. Listener: Implications for education? Speaker: Early language learning should be a national priority. Listener: Thank you for these clarifications.",
    "points": [
      {
        "point": 1,
        "male_lines": ["La thèse de Sapir-Whorf suggère que la langue façonne notre pensée."],
        "female_lines": ["Vous voulez dire que nous ne pouvons pas penser hors de notre langue ?"]
      },
      {
        "point": 2,
        "male_lines": ["C'est une version forte. La version faible dit seulement que la langue influence la perception."],
        "female_lines": ["Quel exemple concret ?"]
      },
      {
        "point": 3,
        "male_lines": ["Les Inuits auraient plusieurs mots pour la neige, percevant ainsi des nuances que nous ne voyons pas."],
        "female_lines": ["Cela a-t-il été prouvé ?"]
      },
      {
        "point": 4,
        "male_lines": ["C'est débattu, mais l'idée reste fascinante."],
        "female_lines": ["Et pour le bilinguisme ?"]
      },
      {
        "point": 5,
        "male_lines": ["Les bilingues développent souvent une flexibilité cognitive supérieure."],
        "female_lines": ["Donc apprendre une langue change notre cerveau ?"]
      },
      {
        "point": 6,
        "male_lines": ["Exactement, cela crée de nouvelles connexions neuronales."],
        "female_lines": ["Implications pour l'éducation ?"]
      },
      {
        "point": 7,
        "male_lines": ["L'apprentissage précoce des langues devrait être une priorité nationale."],
        "female_lines": ["Merci pour ces éclaircissements."]
      },
      {
        "point": 8,
        "male_lines": [],
        "female_lines": []
      },
      {
        "point": 9,
        "male_lines": [],
        "female_lines": []
      },
      {
        "point": 10,
        "male_lines": [],
        "female_lines": []
      }
    ]
  },
  {
    "id": 37,
    "section": "H",
    "theme": "Economic theory",
    "question": "Quel modèle économique est critiqué ?",
    "options": [
      { "id": "A", "text": "Le keynésianisme", "image_prompt": "" },
      { "id": "B", "text": "Le néolibéralisme", "image_prompt": "" },
      { "id": "C", "text": "Le marxisme", "image_prompt": "" },
      { "id": "D", "text": "L'économie planifiée", "image_prompt": "" }
    ],
    "correct": 1,
    "transcript_fr": "Économiste: Le modèle néolibéral dominant depuis les années 80 montre ses limites. Étudiant: Que remplacerait-il ? Économiste: Une économie plus régulée, axée sur le bien-être plutôt que la croissance. Étudiant: Mais la croissance crée l'emploi ? Économiste: Oui, mais elle accroît aussi les inégalités. Étudiant: Quelle alternative concrète ? Économiste: L'économie circulaire et la décroissance sélective. Étudiant: Les entreprises accepteront ? Économiste: Elles devront s'adapter aux nouvelles réglementations. Étudiant: Le Québec est-il prêt ? Économiste: Nous avons des avantages avec notre hydroélectricité. Étudiant: Risques de récession ? Économiste: Une transition mal gérée oui, mais une transition réussie est possible. Étudiant: Merci professeur pour cette analyse.",
    "transcript_en": "Economist: The neoliberal model dominant since the 1980s is showing its limits. Student: What would replace it? Economist: A more regulated economy, focused on well-being rather than growth. Student: But growth creates jobs? Economist: Yes, but it also increases inequalities. Student: What concrete alternative? Economist: Circular economy and selective degrowth. Student: Will companies accept? Economist: They will have to adapt to new regulations. Student: Is Quebec ready? Economist: We have advantages with our hydroelectricity. Student: Recession risks? Economist: A poorly managed transition yes, but a successful transition is possible. Student: Thank you professor for this analysis.",
    "points": [
      {
        "point": 1,
        "male_lines": ["Le modèle néolibéral dominant depuis les années 80 montre ses limites."],
        "female_lines": ["Que remplacerait-il ?"]
      },
      {
        "point": 2,
        "male_lines": ["Une économie plus régulée, axée sur le bien-être plutôt que la croissance."],
        "female_lines": ["Mais la croissance crée l'emploi ?"]
      },
      {
        "point": 3,
        "male_lines": ["Oui, mais elle accroît aussi les inégalités."],
        "female_lines": ["Quelle alternative concrète ?"]
      },
      {
        "point": 4,
        "male_lines": ["L'économie circulaire et la décroissance sélective."],
        "female_lines": ["Les entreprises accepteront ?"]
      },
      {
        "point": 5,
        "male_lines": ["Elles devront s'adapter aux nouvelles réglementations."],
        "female_lines": ["Le Québec est-il prêt ?"]
      },
      {
        "point": 6,
        "male_lines": ["Nous avons des avantages avec notre hydroélectricité."],
        "female_lines": ["Risques de récession ?"]
      },
      {
        "point": 7,
        "male_lines": ["Une transition mal gérée oui, mais une transition réussie est possible."],
        "female_lines": ["Merci professeur pour cette analyse."]
      },
      {
        "point": 8,
        "male_lines": [],
        "female_lines": []
      },
      {
        "point": 9,
        "male_lines": [],
        "female_lines": []
      },
      {
        "point": 10,
        "male_lines": [],
        "female_lines": []
      }
    ]
  },
  {
    "id": 38,
    "section": "H",
    "theme": "Artificial consciousness",
    "question": "Quelle question fondamentale est abordée ?",
    "options": [
      { "id": "A", "text": "L'éthique des robots", "image_prompt": "" },
      { "id": "B", "text": "La conscience artificielle", "image_prompt": "" },
      { "id": "C", "text": "Le remplacement des emplois", "image_prompt": "" },
      { "id": "D", "text": "La sécurité informatique", "image_prompt": "" }
    ],
    "correct": 1,
    "transcript_fr": "Chercheur: Peut-on créer une machine consciente ? Philosophe: Cela dépend de notre définition de la conscience. Chercheur: Les réseaux de neurones imitent le cerveau humain. Philosophe: L'imitation n'est pas la duplication. Chercheur: Mais si le comportement est identique ? Philosophe: Le test de Turing n'est pas suffisant. Chercheur: Quel critère alors ? Philosophe: L'expérience subjective, le qualia. Chercheur: Comment la mesurer ? Philosophe: C'est le problème difficile de la conscience. Chercheur: Implications éthiques ? Philosophe: Si une IA est consciente, nous devons lui accorder des droits. Chercheur: Une perspective lointaine ? Philosophe: Pas autant qu'on le pense, il faut réfléchir maintenant.",
    "transcript_en": "Researcher: Can we create a conscious machine? Philosopher: It depends on our definition of consciousness. Researcher: Neural networks imitate the human brain. Philosopher: Imitation is not duplication. Researcher: But if the behavior is identical? Philosopher: The Turing test is not sufficient. Researcher: What criterion then? Philosopher: Subjective experience, qualia. Researcher: How to measure it? Philosopher: That's the hard problem of consciousness. Researcher: Ethical implications? Philosopher: If an AI is conscious, we must grant it rights. Researcher: A distant perspective? Philosopher: Not as much as we think, we must reflect now.",
    "points": [
      {
        "point": 1,
        "male_lines": ["Peut-on créer une machine consciente ?"],
        "female_lines": ["Cela dépend de notre définition de la conscience."]
      },
      {
        "point": 2,
        "male_lines": ["Les réseaux de neurones imitent le cerveau humain."],
        "female_lines": ["L'imitation n'est pas la duplication."]
      },
      {
        "point": 3,
        "male_lines": ["Mais si le comportement est identique ?"],
        "female_lines": ["Le test de Turing n'est pas suffisant."]
      },
      {
        "point": 4,
        "male_lines": ["Quel critère alors ?"],
        "female_lines": ["L'expérience subjective, le qualia."]
      },
      {
        "point": 5,
        "male_lines": ["Comment la mesurer ?"],
        "female_lines": ["C'est le problème difficile de la conscience."]
      },
      {
        "point": 6,
        "male_lines": ["Implications éthiques ?"],
        "female_lines": ["Si une IA est consciente, nous devons lui accorder des droits."]
      },
      {
        "point": 7,
        "male_lines": ["Une perspective lointaine ?"],
        "female_lines": ["Pas autant qu'on le pense, il faut réfléchir maintenant."]
      },
      {
        "point": 8,
        "male_lines": [],
        "female_lines": []
      },
      {
        "point": 9,
        "male_lines": [],
        "female_lines": []
      },
      {
        "point": 10,
        "male_lines": [],
        "female_lines": []
      }
    ]
  },
  {
    "id": 39,
    "section": "H",
    "theme": "Urban sociology",
    "question": "Quel phénomène urbain est analysé ?",
    "options": [
      { "id": "A", "text": "La gentrification", "image_prompt": "" },
      { "id": "B", "text": "L'étalement urbain", "image_prompt": "" },
      { "id": "C", "text": "La ghettoïsation", "image_prompt": "" },
      { "id": "D", "text": "La revitalisation", "image_prompt": "" }
    ],
    "correct": 0,
    "transcript_fr": "Sociologue: La gentrification transforme nos quartiers populaires. Journaliste: C'est positif non, des quartiers plus propres ? Sociologue: Oui mais les habitants historiques sont expulsés par les loyers. Journaliste: Qui sont les gentrifieurs ? Sociologue: Souvent des jeunes professionnels, des artistes d'abord, puis les classes moyennes supérieures. Journaliste: Le Mile-End en est l'exemple ? Sociologue: Typique. De quartier ouvrier à bobo en vingt ans. Journaliste: Solutions possibles ? Sociologue: Le logement social et les coopératives d'habitation. Journaliste: Le rôle de la mairie ? Sociologue: Essentiel pour réguler via le zonage. Journaliste: Les commerces locaux ? Sociologue: Ils disparaissent remplacés par des chaînes. Journaliste: Un équilibre possible ? Sociologue: Difficile mais nécessaire pour la mixité sociale.",
    "transcript_en": "Sociologist: Gentrification is transforming our working-class neighborhoods. Journalist: Isn't that positive, cleaner neighborhoods? Sociologist: Yes but historic residents are expelled by rents. Journalist: Who are the gentrifiers? Sociologist: Often young professionals, artists first, then upper middle classes. Journalist: Is Mile-End an example? Sociologist: Typical. From working-class to hipster in twenty years. Journalist: Possible solutions? Sociologist: Social housing and housing cooperatives. Journalist: The role of city hall? Sociologist: Essential to regulate via zoning. Journalist: Local businesses? Sociologist: They disappear replaced by chains. Journalist: A possible balance? Sociologist: Difficult but necessary for social diversity.",
    "points": [
      {
        "point": 1,
        "male_lines": ["La gentrification transforme nos quartiers populaires."],
        "female_lines": ["C'est positif non, des quartiers plus propres ?"]
      },
      {
        "point": 2,
        "male_lines": ["Oui mais les habitants historiques sont expulsés par les loyers."],
        "female_lines": ["Qui sont les gentrifieurs ?"]
      },
      {
        "point": 3,
        "male_lines": ["Souvent des jeunes professionnels, des artistes d'abord, puis les classes moyennes supérieures."],
        "female_lines": ["Le Mile-End en est l'exemple ?"]
      },
      {
        "point": 4,
        "male_lines": ["Typique. De quartier ouvrier à bobo en vingt ans."],
        "female_lines": ["Solutions possibles ?"]
      },
      {
        "point": 5,
        "male_lines": ["Le logement social et les coopératives d'habitation."],
        "female_lines": ["Le rôle de la mairie ?"]
      },
      {
        "point": 6,
        "male_lines": ["Essentiel pour réguler via le zonage."],
        "female_lines": ["Les commerces locaux ?"]
      },
      {
        "point": 7,
        "male_lines": ["Ils disparaissent remplacés par des chaînes."],
        "female_lines": ["Un équilibre possible ?"]
      },
      {
        "point": 8,
        "male_lines": ["Difficile mais nécessaire pour la mixité sociale."],
        "female_lines": []
      },
      {
        "point": 9,
        "male_lines": [],
        "female_lines": []
      },
      {
        "point": 10,
        "male_lines": [],
        "female_lines": []
      }
    ]
  },
  {
    "id": 40,
    "section": "H",
    "theme": "Epistemology",
    "question": "Quelle théorie de la connaissance est explorée ?",
    "options": [
      { "id": "A", "text": "Le rationalisme", "image_prompt": "" },
      { "id": "B", "text": "L'empirisme", "image_prompt": "" },
      { "id": "C", "text": "Le constructivisme social", "image_prompt": "" },
      { "id": "D", "text": "Le pragmatisme", "image_prompt": "" }
    ],
    "correct": 2,
    "transcript_fr": "Professeur: Le constructivisme social suggère que la connaissance est créée collectivement. Étudiant: Pas découverte objectivement ? Professeur: Même la science est une construction sociale. Étudiant: Mais la gravité existe indépendamment de nous ? Professeur: Le phénomène oui, mais notre compréhension est médiée par nos concepts. Étudiant: Donc la vérité est relative ? Professeur: Non, elle est contextuelle et historique. Étudiant: Implications pour l'éducation ? Professeur: L'apprentissage doit être actif et collaboratif. Étudiant: Le rôle de l'enseignant change ? Professeur: De transmetteur à facilitateur. Étudiant: Et l'évaluation ? Professeur: Elle doit mesurer la compréhension profonde, pas la mémorisation. Étudiant: Une révolution pédagogique ? Professeur: Nécessaire pour former des esprits critiques.",
    "transcript_en": "Professor: Social constructivism suggests that knowledge is created collectively. Student: Not discovered objectively? Professor: Even science is a social construction. Student: But gravity exists independently of us? Professor: The phenomenon yes, but our understanding is mediated by our concepts. Student: So truth is relative? Professor: No, it is contextual and historical. Student: Implications for education? Professor: Learning must be active and collaborative. Student: The teacher's role changes? Professor: From transmitter to facilitator. Student: And evaluation? Professor: It must measure deep understanding, not memorization. Student: A pedagogical revolution? Professor: Necessary to train critical minds.",
    "points": [
      {
        "point": 1,
        "male_lines": ["Le constructivisme social suggère que la connaissance est créée collectivement."],
        "female_lines": ["Pas découverte objectivement ?"]
      },
      {
        "point": 2,
        "male_lines": ["Même la science est une construction sociale."],
        "female_lines": ["Mais la gravité existe indépendamment de nous ?"]
      },
      {
        "point": 3,
        "male_lines": ["Le phénomène oui, mais notre compréhension est médiée par nos concepts."],
        "female_lines": ["Donc la vérité est relative ?"]
      },
      {
        "point": 4,
        "male_lines": ["Non, elle est contextuelle et historique."],
        "female_lines": ["Implications pour l'éducation ?"]
      },
      {
        "point": 5,
        "male_lines": ["L'apprentissage doit être actif et collaboratif."],
        "female_lines": ["Le rôle de l'enseignant change ?"]
      },
      {
        "point": 6,
        "male_lines": ["De transmetteur à facilitateur."],
        "female_lines": ["Et l'évaluation ?"]
      },
      {
        "point": 7,
        "male_lines": ["Elle doit mesurer la compréhension profonde, pas la mémorisation."],
        "female_lines": ["Une révolution pédagogique ?"]
      },
      {
        "point": 8,
        "male_lines": ["Nécessaire pour former des esprits critiques."],
        "female_lines": []
      },
      {
        "point": 9,
        "male_lines": [],
        "female_lines": []
      },
      {
        "point": 10,
        "male_lines": [],
        "female_lines": []
      }
    ]
  }
]